Workbook
Name Slicer_Indicators: #N/A
Name Slicer_Month: #N/A
Name Slicer_Traffic: #N/A
Name Slicer_Year: #N/A

Sheet DASHBOARD

Sheet Sales

Sheet Coverage

Sheet Traffic

Sheet Processing
B1: =ISNUMBER(MATCH(B2,Control!$A$51:$A$53,0)) -> TRUE | C1: =ISNUMBER(MATCH(C2,Control!$A$51:$A$53,0)) -> TRUE | D1: =ISNUMBER(MATCH(D2,Control!$A$51:$A$53,0)) -> TRUE | H1: TRUE | I1: toggle | J1: Traffic Sources | L1: =SUM(K2:K4) -> 0.69333333 | O1: Year | P1: indent | Q1: Subscribers | R1: Cursor
A2: Month | B2: Revenue | C2: Expenses | D2: Profit | E2: Cursor R | F2: Cursor E | G2: Cursor P | H2: Sales Target | I2: =IF($H$1,10,0) -> 10 | J2: Referral | K2: =GETPIVOTDATA(""&J2,Control!$A$3) -> 0.12666667 | L2: Label | O2: 2025 | P2: =$P$6 -> 843.56 | Q2: =GETPIVOTDATA(""&Q$1,Control!$A$42,"Year",O2) -> 3873 | R2: =IF(ISNUMBER(MATCH(O2,Control!$A$36:$A$39,0)),Q2,NA()) -> #N/A
A3: JAN | B3: =IF(B$1,GETPIVOTDATA(""&B$2,Control!$A$20,"Month",""&$A3),NA()) -> 59019 | C3: =IF(C$1,GETPIVOTDATA(""&C$2,Control!$A$20,"Month",""&$A3),NA()) -> 67541 | D3: =IF(D$1,GETPIVOTDATA(""&D$2,Control!$A$20,"Month",""&$A3),NA()) -> -8522 | E3: =IF(ISNUMBER(GETPIVOTDATA(""&B$2,Control!$A$3,"Month",""&$A3)),B3,NA()) -> #N/A | F3: =IF(ISNUMBER(GETPIVOTDATA(""&C$2,Control!$A$3,"Month",""&$A3)),C3,NA()) -> #N/A | G3: =IF(ISNUMBER(GETPIVOTDATA(""&D$2,Control!$A$3,"Month",""&$A3)),D3,NA()) -> #N/A | H3: =IF($H$1,GETPIVOTDATA("Sum of Sales Target",Control!$A$20,"Month",""&A3),NA()) -> 75000 | I3: =IF($H$1,0,10) -> 0 | J3: Social | K3: =GETPIVOTDATA(""&J3,Control!$A$3) -> 0.39333333 | L3: =J2&CHAR(10)&J3&CHAR(10)&J4&CHAR(10)&J5 -> Referral Social Organic Other | O3: 2026 | P3: =$P$6 -> 843.56 | Q3: =GETPIVOTDATA(""&Q$1,Control!$A$42,"Year",O3) -> 9235 | R3: =IF(ISNUMBER(MATCH(O3,Control!$A$36:$A$39,0)),Q3,NA()) -> #N/A
A4: FEB | B4: =IF(B$1,GETPIVOTDATA(""&B$2,Control!$A$20,"Month",""&$A4),NA()) -> 81135 | C4: =IF(C$1,GETPIVOTDATA(""&C$2,Control!$A$20,"Month",""&$A4),NA()) -> 62626 | D4: =IF(D$1,GETPIVOTDATA(""&D$2,Control!$A$20,"Month",""&$A4),NA()) -> 18509 | E4: =IF(ISNUMBER(GETPIVOTDATA(""&B$2,Control!$A$3,"Month",""&$A4)),B4,NA()) -> 81135 | F4: =IF(ISNUMBER(GETPIVOTDATA(""&C$2,Control!$A$3,"Month",""&$A4)),C4,NA()) -> 62626 | G4: =IF(ISNUMBER(GETPIVOTDATA(""&D$2,Control!$A$3,"Month",""&$A4)),D4,NA()) -> 18509 | H4: =IF($H$1,GETPIVOTDATA("Sum of Sales Target",Control!$A$20,"Month",""&A4),NA()) -> 75000 | J4: Organic | K4: =GETPIVOTDATA(""&J4,Control!$A$3) -> 0.17333333 | L4: =TEXT(K2,"0%")&CHAR(10)&TEXT(K3,"0%")&CHAR(10)&TEXT(K4,"0%")&CHAR(10)&TEXT(K5,"0%") -> 13% 39% 17% 31% | O4: 2027 | P4: =$P$6 -> 843.56 | Q4: =GETPIVOTDATA(""&Q$1,Control!$A$42,"Year",O4) -> 15418 | R4: =IF(ISNUMBER(MATCH(O4,Control!$A$36:$A$39,0)),Q4,NA()) -> 15418
A5: MAR | B5: =IF(B$1,GETPIVOTDATA(""&B$2,Control!$A$20,"Month",""&$A5),NA()) -> 84342 | C5: =IF(C$1,GETPIVOTDATA(""&C$2,Control!$A$20,"Month",""&$A5),NA()) -> 68752 | D5: =IF(D$1,GETPIVOTDATA(""&D$2,Control!$A$20,"Month",""&$A5),NA()) -> 15590 | E5: =IF(ISNUMBER(GETPIVOTDATA(""&B$2,Control!$A$3,"Month",""&$A5)),B5,NA()) -> #N/A | F5: =IF(ISNUMBER(GETPIVOTDATA(""&C$2,Control!$A$3,"Month",""&$A5)),C5,NA()) -> #N/A | G5: =IF(ISNUMBER(GETPIVOTDATA(""&D$2,Control!$A$3,"Month",""&$A5)),D5,NA()) -> #N/A | H5: =IF($H$1,GETPIVOTDATA("Sum of Sales Target",Control!$A$20,"Month",""&A5),NA()) -> 75000 | I5: Indicators | J5: Other | K5: =GETPIVOTDATA(""&J5,Control!$A$3) -> 0.30666667 | O5: 2028 | P5: =$P$6 -> 843.56 | Q5: =GETPIVOTDATA(""&Q$1,Control!$A$42,"Year",O5) -> 21089 | R5: =IF(ISNUMBER(MATCH(O5,Control!$A$36:$A$39,0)),Q5,NA()) -> #N/A
A6: APR | B6: =IF(B$1,GETPIVOTDATA(""&B$2,Control!$A$20,"Month",""&$A6),NA()) -> 73245 | C6: =IF(C$1,GETPIVOTDATA(""&C$2,Control!$A$20,"Month",""&$A6),NA()) -> 78653 | D6: =IF(D$1,GETPIVOTDATA(""&D$2,Control!$A$20,"Month",""&$A6),NA()) -> -5408 | E6: =IF(ISNUMBER(GETPIVOTDATA(""&B$2,Control!$A$3,"Month",""&$A6)),B6,NA()) -> 73245 | F6: =IF(ISNUMBER(GETPIVOTDATA(""&C$2,Control!$A$3,"Month",""&$A6)),C6,NA()) -> 78653 | G6: =IF(ISNUMBER(GETPIVOTDATA(""&D$2,Control!$A$3,"Month",""&$A6)),D6,NA()) -> -5408 | H6: =IF($H$1,GETPIVOTDATA("Sum of Sales Target",Control!$A$20,"Month",""&A6),NA()) -> 75000 | I6: Revenue | P6: =MAX(Q2:Q5)*4% -> 843.56 | R6: =GETPIVOTDATA("Sum of Subscribers",Control!$A$3) -> 3611
A7: MAY | B7: =IF(B$1,GETPIVOTDATA(""&B$2,Control!$A$20,"Month",""&$A7),NA()) -> 57139 | C7: =IF(C$1,GETPIVOTDATA(""&C$2,Control!$A$20,"Month",""&$A7),NA()) -> 73540 | D7: =IF(D$1,GETPIVOTDATA(""&D$2,Control!$A$20,"Month",""&$A7),NA()) -> -16401 | E7: =IF(ISNUMBER(GETPIVOTDATA(""&B$2,Control!$A$3,"Month",""&$A7)),B7,NA()) -> #N/A | F7: =IF(ISNUMBER(GETPIVOTDATA(""&C$2,Control!$A$3,"Month",""&$A7)),C7,NA()) -> #N/A | G7: =IF(ISNUMBER(GETPIVOTDATA(""&D$2,Control!$A$3,"Month",""&$A7)),D7,NA()) -> #N/A | H7: =IF($H$1,GETPIVOTDATA("Sum of Sales Target",Control!$A$20,"Month",""&A7),NA()) -> 75000 | I7: Expenses | K7: District | L7: Coverage | M7: Coverage Target | N7: =IF($H$1,H17,"") -> Target | P7: Leads | Q7: Deals
A8: JUN | B8: =IF(B$1,GETPIVOTDATA(""&B$2,Control!$A$20,"Month",""&$A8),NA()) -> 44835 | C8: =IF(C$1,GETPIVOTDATA(""&C$2,Control!$A$20,"Month",""&$A8),NA()) -> 61426 | D8: =IF(D$1,GETPIVOTDATA(""&D$2,Control!$A$20,"Month",""&$A8),NA()) -> -16591 | E8: =IF(ISNUMBER(GETPIVOTDATA(""&B$2,Control!$A$3,"Month",""&$A8)),B8,NA()) -> #N/A | F8: =IF(ISNUMBER(GETPIVOTDATA(""&C$2,Control!$A$3,"Month",""&$A8)),C8,NA()) -> #N/A | G8: =IF(ISNUMBER(GETPIVOTDATA(""&D$2,Control!$A$3,"Month",""&$A8)),D8,NA()) -> #N/A | H8: =IF($H$1,GETPIVOTDATA("Sum of Sales Target",Control!$A$20,"Month",""&A8),NA()) -> 75000 | I8: Profit | J8: North | K8: N | L8: =GETPIVOTDATA(""&K8,Control!$A$3) -> 0.8 | M8: =IF($H$1,GETPIVOTDATA("Max of Coverage Target",Control!$A$3),NA()) -> 0.8 | N8: =IF($H$1,M15,"") -> 0.8 | P8: =GETPIVOTDATA("Sum of Leads",Control!$A$3) -> 8422 | Q8: =GETPIVOTDATA("Sum of Deals",Control!$A$3) -> 5058
A9: JUL | B9: =IF(B$1,GETPIVOTDATA(""&B$2,Control!$A$20,"Month",""&$A9),NA()) -> 52221 | C9: =IF(C$1,GETPIVOTDATA(""&C$2,Control!$A$20,"Month",""&$A9),NA()) -> 58031 | D9: =IF(D$1,GETPIVOTDATA(""&D$2,Control!$A$20,"Month",""&$A9),NA()) -> -5810 | E9: =IF(ISNUMBER(GETPIVOTDATA(""&B$2,Control!$A$3,"Month",""&$A9)),B9,NA()) -> 52221 | F9: =IF(ISNUMBER(GETPIVOTDATA(""&C$2,Control!$A$3,"Month",""&$A9)),C9,NA()) -> 58031 | G9: =IF(ISNUMBER(GETPIVOTDATA(""&D$2,Control!$A$3,"Month",""&$A9)),D9,NA()) -> -5810 | H9: =IF($H$1,GETPIVOTDATA("Sum of Sales Target",Control!$A$20,"Month",""&A9),NA()) -> 75000 | J9: Northeast | K9: NE | L9: =GETPIVOTDATA(""&K9,Control!$A$3) -> 0.76666667 | M9: =IF($H$1,GETPIVOTDATA("Max of Coverage Target",Control!$A$3),NA()) -> 0.8 | P9: Conversion
A10: AUG | B10: =IF(B$1,GETPIVOTDATA(""&B$2,Control!$A$20,"Month",""&$A10),NA()) -> 96718 | C10: =IF(C$1,GETPIVOTDATA(""&C$2,Control!$A$20,"Month",""&$A10),NA()) -> 65713 | D10: =IF(D$1,GETPIVOTDATA(""&D$2,Control!$A$20,"Month",""&$A10),NA()) -> 31005 | E10: =IF(ISNUMBER(GETPIVOTDATA(""&B$2,Control!$A$3,"Month",""&$A10)),B10,NA()) -> #N/A | F10: =IF(ISNUMBER(GETPIVOTDATA(""&C$2,Control!$A$3,"Month",""&$A10)),C10,NA()) -> #N/A | G10: =IF(ISNUMBER(GETPIVOTDATA(""&D$2,Control!$A$3,"Month",""&$A10)),D10,NA()) -> #N/A | H10: =IF($H$1,GETPIVOTDATA("Sum of Sales Target",Control!$A$20,"Month",""&A10),NA()) -> 75000 | J10: East | K10: E | L10: =GETPIVOTDATA(""&K10,Control!$A$3) -> 0.76666667 | M10: =IF($H$1,GETPIVOTDATA("Max of Coverage Target",Control!$A$3),NA()) -> 0.8 | P10: =Q8/P8 -> 0.60056994 | Q10: =1-P10 -> 0.39943006
A11: SEP | B11: =IF(B$1,GETPIVOTDATA(""&B$2,Control!$A$20,"Month",""&$A11),NA()) -> 111028 | C11: =IF(C$1,GETPIVOTDATA(""&C$2,Control!$A$20,"Month",""&$A11),NA()) -> 80943 | D11: =IF(D$1,GETPIVOTDATA(""&D$2,Control!$A$20,"Month",""&$A11),NA()) -> 30085 | E11: =IF(ISNUMBER(GETPIVOTDATA(""&B$2,Control!$A$3,"Month",""&$A11)),B11,NA()) -> #N/A | F11: =IF(ISNUMBER(GETPIVOTDATA(""&C$2,Control!$A$3,"Month",""&$A11)),C11,NA()) -> #N/A | G11: =IF(ISNUMBER(GETPIVOTDATA(""&D$2,Control!$A$3,"Month",""&$A11)),D11,NA()) -> #N/A | H11: =IF($H$1,GETPIVOTDATA("Sum of Sales Target",Control!$A$20,"Month",""&A11),NA()) -> 75000 | J11: Southeast | K11: SE | L11: =GETPIVOTDATA(""&K11,Control!$A$3) -> 0.73333333 | M11: =IF($H$1,GETPIVOTDATA("Max of Coverage Target",Control!$A$3),NA()) -> 0.8
A12: OCT | B12: =IF(B$1,GETPIVOTDATA(""&B$2,Control!$A$20,"Month",""&$A12),NA()) -> 105644 | C12: =IF(C$1,GETPIVOTDATA(""&C$2,Control!$A$20,"Month",""&$A12),NA()) -> 89819 | D12: =IF(D$1,GETPIVOTDATA(""&D$2,Control!$A$20,"Month",""&$A12),NA()) -> 15825 | E12: =IF(ISNUMBER(GETPIVOTDATA(""&B$2,Control!$A$3,"Month",""&$A12)),B12,NA()) -> #N/A | F12: =IF(ISNUMBER(GETPIVOTDATA(""&C$2,Control!$A$3,"Month",""&$A12)),C12,NA()) -> #N/A | G12: =IF(ISNUMBER(GETPIVOTDATA(""&D$2,Control!$A$3,"Month",""&$A12)),D12,NA()) -> #N/A | H12: =IF($H$1,GETPIVOTDATA("Sum of Sales Target",Control!$A$20,"Month",""&A12),NA()) -> 75000 | J12: South | K12: S | L12: =GETPIVOTDATA(""&K12,Control!$A$3) -> 0.73333333 | M12: =IF($H$1,GETPIVOTDATA("Max of Coverage Target",Control!$A$3),NA()) -> 0.8 | P12: Target | Q12: =E15/H15 -> 0.91822667
A13: NOV | B13: =IF(B$1,GETPIVOTDATA(""&B$2,Control!$A$20,"Month",""&$A13),NA()) -> 77026 | C13: =IF(C$1,GETPIVOTDATA(""&C$2,Control!$A$20,"Month",""&$A13),NA()) -> 85029 | D13: =IF(D$1,GETPIVOTDATA(""&D$2,Control!$A$20,"Month",""&$A13),NA()) -> -8003 | E13: =IF(ISNUMBER(GETPIVOTDATA(""&B$2,Control!$A$3,"Month",""&$A13)),B13,NA()) -> #N/A | F13: =IF(ISNUMBER(GETPIVOTDATA(""&C$2,Control!$A$3,"Month",""&$A13)),C13,NA()) -> #N/A | G13: =IF(ISNUMBER(GETPIVOTDATA(""&D$2,Control!$A$3,"Month",""&$A13)),D13,NA()) -> #N/A | H13: =IF($H$1,GETPIVOTDATA("Sum of Sales Target",Control!$A$20,"Month",""&A13),NA()) -> 75000 | J13: Southwest | K13: SW | L13: =GETPIVOTDATA(""&K13,Control!$A$3) -> 0.73333333 | M13: =IF($H$1,GETPIVOTDATA("Max of Coverage Target",Control!$A$3),NA()) -> 0.8 | P13: =IF($Q$12>100%,0,$Q$12) -> 0.91822667
A14: DEC | B14: =IF(B$1,GETPIVOTDATA(""&B$2,Control!$A$20,"Month",""&$A14),NA()) -> 90717 | C14: =IF(C$1,GETPIVOTDATA(""&C$2,Control!$A$20,"Month",""&$A14),NA()) -> 74016 | D14: =IF(D$1,GETPIVOTDATA(""&D$2,Control!$A$20,"Month",""&$A14),NA()) -> 16701 | E14: =IF(ISNUMBER(GETPIVOTDATA(""&B$2,Control!$A$3,"Month",""&$A14)),B14,NA()) -> #N/A | F14: =IF(ISNUMBER(GETPIVOTDATA(""&C$2,Control!$A$3,"Month",""&$A14)),C14,NA()) -> #N/A | G14: =IF(ISNUMBER(GETPIVOTDATA(""&D$2,Control!$A$3,"Month",""&$A14)),D14,NA()) -> #N/A | H14: =IF($H$1,GETPIVOTDATA("Sum of Sales Target",Control!$A$20,"Month",""&A14),NA()) -> 75000 | J14: West | K14: W | L14: =GETPIVOTDATA(""&K14,Control!$A$3) -> 0.7 | M14: =IF($H$1,GETPIVOTDATA("Max of Coverage Target",Control!$A$3),NA()) -> 0.8 | P14: =IF($Q$12>100%,0,1-P13) -> 0.081773333
E15: =GETPIVOTDATA(""&B2,Control!$A$3) -> 206601 | F15: =GETPIVOTDATA(""&C2,Control!$A$3) -> 199310 | G15: =GETPIVOTDATA(""&D2,Control!$A$3) -> 7291 | H15: =GETPIVOTDATA(""&H2,Control!$A$3) -> 225000 | J15: Northwest | K15: NW | L15: =GETPIVOTDATA(""&K15,Control!$A$3) -> 0.7 | M15: =IF($H$1,GETPIVOTDATA("Max of Coverage Target",Control!$A$3),NA()) -> 0.8 | P15: =IF($Q$12>100%,Q12-1,0) -> 0
C16: =ISNUMBER(MATCH(C17,Control!$A$58:$A$59,0)) -> TRUE | D16: =ISNUMBER(MATCH(D17,Control!$A$58:$A$59,0)) -> TRUE | L16: =AVERAGE(L8:L15) -> 0.74166667 | P16: =IF($Q$12>100%,1-P15,0) -> 0
A17: Month | B17: indent | C17: Standart | D17: Premium | E17: indent C | F17: Cursor S | G17: Cursor P | H17: Target | I17: Tariffs | K17: Month | L17: Referral | M17: Social | N17: Organic | O17: Other | P17: Cursor | Q17: Traffic
A18: JAN | B18: =$B$30 -> 50.76 | C18: =IF(C$16,GETPIVOTDATA(""&C$17,Control!$A$20,"Month",""&$A18),NA()) -> 538 | D18: =IF(D$16,GETPIVOTDATA(""&D$17,Control!$A$20,"Month",""&$A18),NA()) -> 510 | E18: =B18 -> 50.76 | F18: =IF(ISNUMBER(GETPIVOTDATA("Sum of Revenue",Control!$A$3,"Month",""&$A18)),C18,NA()) -> #N/A | G18: =IF(ISNUMBER(GETPIVOTDATA("Sum of Revenue",Control!$A$3,"Month",""&$A18)),D18,NA()) -> #N/A | H18: =IF($H$1,GETPIVOTDATA(""&H$30,Control!$A$20,"Month",""&A3),NA()) -> 1400 | I18: Standart | K18: JAN | L18: =IF(L$30,GETPIVOTDATA(""&L$17,Control!$A$20,"Month",""&$K18),NA()) -> #N/A | M18: =IF(M$30,GETPIVOTDATA(""&M$17,Control!$A$20,"Month",""&$K18),NA()) -> 0.33 | N18: =IF(N$30,GETPIVOTDATA(""&N$17,Control!$A$20,"Month",""&$K18),NA()) -> #N/A | O18: =IF(O$30,GETPIVOTDATA(""&O$17,Control!$A$20,"Month",""&$K18),NA()) -> #N/A | P18: {=IF(ISNA(F18),F18,MAX(IFERROR($L$18:$O$29,0)+10%))} -> #N/A | Q18: Referral
A19: FEB | B19: =$B$30 -> 50.76 | C19: =IF(C$16,GETPIVOTDATA(""&C$17,Control!$A$20,"Month",""&$A19),NA()) -> 797 | D19: =IF(D$16,GETPIVOTDATA(""&D$17,Control!$A$20,"Month",""&$A19),NA()) -> 318 | E19: =B19 -> 50.76 | F19: =IF(ISNUMBER(GETPIVOTDATA("Sum of Revenue",Control!$A$3,"Month",""&$A19)),C19,NA()) -> 797 | G19: =IF(ISNUMBER(GETPIVOTDATA("Sum of Revenue",Control!$A$3,"Month",""&$A19)),D19,NA()) -> 318 | H19: =IF($H$1,GETPIVOTDATA(""&H$30,Control!$A$20,"Month",""&A4),NA()) -> 1400 | I19: Premium | K19: FEB | L19: =IF(L$30,GETPIVOTDATA(""&L$17,Control!$A$20,"Month",""&$K19),NA()) -> #N/A | M19: =IF(M$30,GETPIVOTDATA(""&M$17,Control!$A$20,"Month",""&$K19),NA()) -> 0.45 | N19: =IF(N$30,GETPIVOTDATA(""&N$17,Control!$A$20,"Month",""&$K19),NA()) -> #N/A | O19: =IF(O$30,GETPIVOTDATA(""&O$17,Control!$A$20,"Month",""&$K19),NA()) -> #N/A | P19: {=IF(ISNA(F19),F19,MAX(IFERROR($L$18:$O$29,0)+10%))} -> 0.6 | Q19: Social
A20: MAR | B20: =$B$30 -> 50.76 | C20: =IF(C$16,GETPIVOTDATA(""&C$17,Control!$A$20,"Month",""&$A20),NA()) -> 565 | D20: =IF(D$16,GETPIVOTDATA(""&D$17,Control!$A$20,"Month",""&$A20),NA()) -> 540 | E20: =B20 -> 50.76 | F20: =IF(ISNUMBER(GETPIVOTDATA("Sum of Revenue",Control!$A$3,"Month",""&$A20)),C20,NA()) -> #N/A | G20: =IF(ISNUMBER(GETPIVOTDATA("Sum of Revenue",Control!$A$3,"Month",""&$A20)),D20,NA()) -> #N/A | H20: =IF($H$1,GETPIVOTDATA(""&H$30,Control!$A$20,"Month",""&A5),NA()) -> 1400 | K20: MAR | L20: =IF(L$30,GETPIVOTDATA(""&L$17,Control!$A$20,"Month",""&$K20),NA()) -> #N/A | M20: =IF(M$30,GETPIVOTDATA(""&M$17,Control!$A$20,"Month",""&$K20),NA()) -> 0.38 | N20: =IF(N$30,GETPIVOTDATA(""&N$17,Control!$A$20,"Month",""&$K20),NA()) -> #N/A | O20: =IF(O$30,GETPIVOTDATA(""&O$17,Control!$A$20,"Month",""&$K20),NA()) -> #N/A | P20: {=IF(ISNA(F20),F20,MAX(IFERROR($L$18:$O$29,0)+10%))} -> #N/A | Q20: Organic
A21: APR | B21: =$B$30 -> 50.76 | C21: =IF(C$16,GETPIVOTDATA(""&C$17,Control!$A$20,"Month",""&$A21),NA()) -> 882 | D21: =IF(D$16,GETPIVOTDATA(""&D$17,Control!$A$20,"Month",""&$A21),NA()) -> 325 | E21: =B21 -> 50.76 | F21: =IF(ISNUMBER(GETPIVOTDATA("Sum of Revenue",Control!$A$3,"Month",""&$A21)),C21,NA()) -> 882 | G21: =IF(ISNUMBER(GETPIVOTDATA("Sum of Revenue",Control!$A$3,"Month",""&$A21)),D21,NA()) -> 325 | H21: =IF($H$1,GETPIVOTDATA(""&H$30,Control!$A$20,"Month",""&A6),NA()) -> 1400 | I21: =IF(H1,"Total Target","") -> Total Target | K21: APR | L21: =IF(L$30,GETPIVOTDATA(""&L$17,Control!$A$20,"Month",""&$K21),NA()) -> #N/A | M21: =IF(M$30,GETPIVOTDATA(""&M$17,Control!$A$20,"Month",""&$K21),NA()) -> 0.41 | N21: =IF(N$30,GETPIVOTDATA(""&N$17,Control!$A$20,"Month",""&$K21),NA()) -> #N/A | O21: =IF(O$30,GETPIVOTDATA(""&O$17,Control!$A$20,"Month",""&$K21),NA()) -> #N/A | P21: {=IF(ISNA(F21),F21,MAX(IFERROR($L$18:$O$29,0)+10%))} -> 0.6 | Q21: Other
A22: MAY | B22: =$B$30 -> 50.76 | C22: =IF(C$16,GETPIVOTDATA(""&C$17,Control!$A$20,"Month",""&$A22),NA()) -> 597 | D22: =IF(D$16,GETPIVOTDATA(""&D$17,Control!$A$20,"Month",""&$A22),NA()) -> 611 | E22: =B22 -> 50.76 | F22: =IF(ISNUMBER(GETPIVOTDATA("Sum of Revenue",Control!$A$3,"Month",""&$A22)),C22,NA()) -> #N/A | G22: =IF(ISNUMBER(GETPIVOTDATA("Sum of Revenue",Control!$A$3,"Month",""&$A22)),D22,NA()) -> #N/A | H22: =IF($H$1,GETPIVOTDATA(""&H$30,Control!$A$20,"Month",""&A7),NA()) -> 1400 | I22: =IF(H1,H18,"") -> 1400 | K22: MAY | L22: =IF(L$30,GETPIVOTDATA(""&L$17,Control!$A$20,"Month",""&$K22),NA()) -> #N/A | M22: =IF(M$30,GETPIVOTDATA(""&M$17,Control!$A$20,"Month",""&$K22),NA()) -> 0.23 | N22: =IF(N$30,GETPIVOTDATA(""&N$17,Control!$A$20,"Month",""&$K22),NA()) -> #N/A | O22: =IF(O$30,GETPIVOTDATA(""&O$17,Control!$A$20,"Month",""&$K22),NA()) -> #N/A | P22: {=IF(ISNA(F22),F22,MAX(IFERROR($L$18:$O$29,0)+10%))} -> #N/A
A23: JUN | B23: =$B$30 -> 50.76 | C23: =IF(C$16,GETPIVOTDATA(""&C$17,Control!$A$20,"Month",""&$A23),NA()) -> 645 | D23: =IF(D$16,GETPIVOTDATA(""&D$17,Control!$A$20,"Month",""&$A23),NA()) -> 616 | E23: =B23 -> 50.76 | F23: =IF(ISNUMBER(GETPIVOTDATA("Sum of Revenue",Control!$A$3,"Month",""&$A23)),C23,NA()) -> #N/A | G23: =IF(ISNUMBER(GETPIVOTDATA("Sum of Revenue",Control!$A$3,"Month",""&$A23)),D23,NA()) -> #N/A | H23: =IF($H$1,GETPIVOTDATA(""&H$30,Control!$A$20,"Month",""&A8),NA()) -> 1400 | K23: JUN | L23: =IF(L$30,GETPIVOTDATA(""&L$17,Control!$A$20,"Month",""&$K23),NA()) -> #N/A | M23: =IF(M$30,GETPIVOTDATA(""&M$17,Control!$A$20,"Month",""&$K23),NA()) -> 0.23 | N23: =IF(N$30,GETPIVOTDATA(""&N$17,Control!$A$20,"Month",""&$K23),NA()) -> #N/A | O23: =IF(O$30,GETPIVOTDATA(""&O$17,Control!$A$20,"Month",""&$K23),NA()) -> #N/A | P23: {=IF(ISNA(F23),F23,MAX(IFERROR($L$18:$O$29,0)+10%))} -> #N/A
A24: JUL | B24: =$B$30 -> 50.76 | C24: =IF(C$16,GETPIVOTDATA(""&C$17,Control!$A$20,"Month",""&$A24),NA()) -> 790 | D24: =IF(D$16,GETPIVOTDATA(""&D$17,Control!$A$20,"Month",""&$A24),NA()) -> 499 | E24: =B24 -> 50.76 | F24: =IF(ISNUMBER(GETPIVOTDATA("Sum of Revenue",Control!$A$3,"Month",""&$A24)),C24,NA()) -> 790 | G24: =IF(ISNUMBER(GETPIVOTDATA("Sum of Revenue",Control!$A$3,"Month",""&$A24)),D24,NA()) -> 499 | H24: =IF($H$1,GETPIVOTDATA(""&H$30,Control!$A$20,"Month",""&A9),NA()) -> 1400 | K24: JUL | L24: =IF(L$30,GETPIVOTDATA(""&L$17,Control!$A$20,"Month",""&$K24),NA()) -> #N/A | M24: =IF(M$30,GETPIVOTDATA(""&M$17,Control!$A$20,"Month",""&$K24),NA()) -> 0.32 | N24: =IF(N$30,GETPIVOTDATA(""&N$17,Control!$A$20,"Month",""&$K24),NA()) -> #N/A | O24: =IF(O$30,GETPIVOTDATA(""&O$17,Control!$A$20,"Month",""&$K24),NA()) -> #N/A | P24: {=IF(ISNA(F24),F24,MAX(IFERROR($L$18:$O$29,0)+10%))} -> 0.6
A25: AUG | B25: =$B$30 -> 50.76 | C25: =IF(C$16,GETPIVOTDATA(""&C$17,Control!$A$20,"Month",""&$A25),NA()) -> 996 | D25: =IF(D$16,GETPIVOTDATA(""&D$17,Control!$A$20,"Month",""&$A25),NA()) -> 431 | E25: =B25 -> 50.76 | F25: =IF(ISNUMBER(GETPIVOTDATA("Sum of Revenue",Control!$A$3,"Month",""&$A25)),C25,NA()) -> #N/A | G25: =IF(ISNUMBER(GETPIVOTDATA("Sum of Revenue",Control!$A$3,"Month",""&$A25)),D25,NA()) -> #N/A | H25: =IF($H$1,GETPIVOTDATA(""&H$30,Control!$A$20,"Month",""&A10),NA()) -> 1400 | K25: AUG | L25: =IF(L$30,GETPIVOTDATA(""&L$17,Control!$A$20,"Month",""&$K25),NA()) -> #N/A | M25: =IF(M$30,GETPIVOTDATA(""&M$17,Control!$A$20,"Month",""&$K25),NA()) -> 0.24 | N25: =IF(N$30,GETPIVOTDATA(""&N$17,Control!$A$20,"Month",""&$K25),NA()) -> #N/A | O25: =IF(O$30,GETPIVOTDATA(""&O$17,Control!$A$20,"Month",""&$K25),NA()) -> #N/A | P25: {=IF(ISNA(F25),F25,MAX(IFERROR($L$18:$O$29,0)+10%))} -> #N/A
A26: SEP | B26: =$B$30 -> 50.76 | C26: =IF(C$16,GETPIVOTDATA(""&C$17,Control!$A$20,"Month",""&$A26),NA()) -> 1183 | D26: =IF(D$16,GETPIVOTDATA(""&D$17,Control!$A$20,"Month",""&$A26),NA()) -> 210 | E26: =B26 -> 50.76 | F26: =IF(ISNUMBER(GETPIVOTDATA("Sum of Revenue",Control!$A$3,"Month",""&$A26)),C26,NA()) -> #N/A | G26: =IF(ISNUMBER(GETPIVOTDATA("Sum of Revenue",Control!$A$3,"Month",""&$A26)),D26,NA()) -> #N/A | H26: =IF($H$1,GETPIVOTDATA(""&H$30,Control!$A$20,"Month",""&A11),NA()) -> 1400 | K26: SEP | L26: =IF(L$30,GETPIVOTDATA(""&L$17,Control!$A$20,"Month",""&$K26),NA()) -> #N/A | M26: =IF(M$30,GETPIVOTDATA(""&M$17,Control!$A$20,"Month",""&$K26),NA()) -> 0.4 | N26: =IF(N$30,GETPIVOTDATA(""&N$17,Control!$A$20,"Month",""&$K26),NA()) -> #N/A | O26: =IF(O$30,GETPIVOTDATA(""&O$17,Control!$A$20,"Month",""&$K26),NA()) -> #N/A | P26: {=IF(ISNA(F26),F26,MAX(IFERROR($L$18:$O$29,0)+10%))} -> #N/A
A27: OCT | B27: =$B$30 -> 50.76 | C27: =IF(C$16,GETPIVOTDATA(""&C$17,Control!$A$20,"Month",""&$A27),NA()) -> 876 | D27: =IF(D$16,GETPIVOTDATA(""&D$17,Control!$A$20,"Month",""&$A27),NA()) -> 516 | E27: =B27 -> 50.76 | F27: =IF(ISNUMBER(GETPIVOTDATA("Sum of Revenue",Control!$A$3,"Month",""&$A27)),C27,NA()) -> #N/A | G27: =IF(ISNUMBER(GETPIVOTDATA("Sum of Revenue",Control!$A$3,"Month",""&$A27)),D27,NA()) -> #N/A | H27: =IF($H$1,GETPIVOTDATA(""&H$30,Control!$A$20,"Month",""&A12),NA()) -> 1400 | K27: OCT | L27: =IF(L$30,GETPIVOTDATA(""&L$17,Control!$A$20,"Month",""&$K27),NA()) -> #N/A | M27: =IF(M$30,GETPIVOTDATA(""&M$17,Control!$A$20,"Month",""&$K27),NA()) -> 0.5 | N27: =IF(N$30,GETPIVOTDATA(""&N$17,Control!$A$20,"Month",""&$K27),NA()) -> #N/A | O27: =IF(O$30,GETPIVOTDATA(""&O$17,Control!$A$20,"Month",""&$K27),NA()) -> #N/A | P27: {=IF(ISNA(F27),F27,MAX(IFERROR($L$18:$O$29,0)+10%))} -> #N/A
A28: NOV | B28: =$B$30 -> 50.76 | C28: =IF(C$16,GETPIVOTDATA(""&C$17,Control!$A$20,"Month",""&$A28),NA()) -> 1101 | D28: =IF(D$16,GETPIVOTDATA(""&D$17,Control!$A$20,"Month",""&$A28),NA()) -> 406 | E28: =B28 -> 50.76 | F28: =IF(ISNUMBER(GETPIVOTDATA("Sum of Revenue",Control!$A$3,"Month",""&$A28)),C28,NA()) -> #N/A | G28: =IF(ISNUMBER(GETPIVOTDATA("Sum of Revenue",Control!$A$3,"Month",""&$A28)),D28,NA()) -> #N/A | H28: =IF($H$1,GETPIVOTDATA(""&H$30,Control!$A$20,"Month",""&A13),NA()) -> 1400 | K28: NOV | L28: =IF(L$30,GETPIVOTDATA(""&L$17,Control!$A$20,"Month",""&$K28),NA()) -> #N/A | M28: =IF(M$30,GETPIVOTDATA(""&M$17,Control!$A$20,"Month",""&$K28),NA()) -> 0.33 | N28: =IF(N$30,GETPIVOTDATA(""&N$17,Control!$A$20,"Month",""&$K28),NA()) -> #N/A | O28: =IF(O$30,GETPIVOTDATA(""&O$17,Control!$A$20,"Month",""&$K28),NA()) -> #N/A | P28: {=IF(ISNA(F28),F28,MAX(IFERROR($L$18:$O$29,0)+10%))} -> #N/A
A29: DEC | B29: =$B$30 -> 50.76 | C29: =IF(C$16,GETPIVOTDATA(""&C$17,Control!$A$20,"Month",""&$A29),NA()) -> 1269 | D29: =IF(D$16,GETPIVOTDATA(""&D$17,Control!$A$20,"Month",""&$A29),NA()) -> 197 | E29: =B29 -> 50.76 | F29: =IF(ISNUMBER(GETPIVOTDATA("Sum of Revenue",Control!$A$3,"Month",""&$A29)),C29,NA()) -> #N/A | G29: =IF(ISNUMBER(GETPIVOTDATA("Sum of Revenue",Control!$A$3,"Month",""&$A29)),D29,NA()) -> #N/A | H29: =IF($H$1,GETPIVOTDATA(""&H$30,Control!$A$20,"Month",""&A14),NA()) -> 1400 | K29: DEC | L29: =IF(L$30,GETPIVOTDATA(""&L$17,Control!$A$20,"Month",""&$K29),NA()) -> #N/A | M29: =IF(M$30,GETPIVOTDATA(""&M$17,Control!$A$20,"Month",""&$K29),NA()) -> 0.3 | N29: =IF(N$30,GETPIVOTDATA(""&N$17,Control!$A$20,"Month",""&$K29),NA()) -> #N/A | O29: =IF(O$30,GETPIVOTDATA(""&O$17,Control!$A$20,"Month",""&$K29),NA()) -> #N/A | P29: {=IF(ISNA(F29),F29,MAX(IFERROR($L$18:$O$29,0)+10%))} -> #N/A
B30: {=MAX(IFERROR(C18:D29,0))*4%} -> 50.76 | F30: =GETPIVOTDATA("Sum of Standart",Control!$A$3) -> 2469 | G30: =GETPIVOTDATA("Sum of Premium",Control!$A$3) -> 1142 | H30: Subscribers Target | L30: =ISNUMBER(MATCH(L17,Control!$A$63:$A$66,0)) -> FALSE | M30: =ISNUMBER(MATCH(M17,Control!$A$63:$A$66,0)) -> TRUE | N30: =ISNUMBER(MATCH(N17,Control!$A$63:$A$66,0)) -> FALSE | O30: =ISNUMBER(MATCH(O17,Control!$A$63:$A$66,0)) -> FALSE

Sheet Control
A3: Row Labels | B3: Sum of Revenue | C3: Sum of Expenses | D3: Sum of Profit | E3: Sum of Subscribers | F3: Sum of Leads | G3: Sum of Deals | H3: Average of Referral | I3: Average of Social | J3: Average of Organic | K3: Average of Other | L3: Average of N | M3: Average of NE | N3: Average of E | O3: Average of SE | P3: Average of S | Q3: Average of SW | R3: Average of W | S3: Average of NW | T3: Sum of Sales Target | U3: Sum of Subscribers Target | V3: Sum of Standart | W3: Sum of Premium | X3: Max of Coverage Target
A4: FEB | B4: 81135 | C4: 62626 | D4: 18509 | E4: 1115 | F4: 2073 | G4: 1661 | H4: 0.22 | I4: 0.45 | J4: 0.22333333 | K4: 0.10666667 | L4: 0.8 | M4: 0.7 | N4: 0.7 | O4: 0.7 | P4: 0.7 | Q4: 0.7 | R4: 0.7 | S4: 0.7 | T4: 75000 | U4: 1400 | V4: 797 | W4: 318 | X4: 0.8
A5: APR | B5: 73245 | C5: 78653 | D5: -5408 | E5: 1207 | F5: 2908 | G5: 1400 | H5: 0.08 | I5: 0.41 | J5: 0.16333333 | K5: 0.34666667 | L5: 0.8 | M5: 0.8 | N5: 0.8 | O5: 0.7 | P5: 0.7 | Q5: 0.7 | R5: 0.7 | S5: 0.7 | T5: 75000 | U5: 1400 | V5: 882 | W5: 325 | X5: 0.8
A6: JUL | B6: 52221 | C6: 58031 | D6: -5810 | E6: 1289 | F6: 3441 | G6: 1997 | H6: 0.08 | I6: 0.32 | J6: 0.13333333 | K6: 0.46666667 | L6: 0.8 | M6: 0.8 | N6: 0.8 | O6: 0.8 | P6: 0.8 | Q6: 0.8 | R6: 0.7 | S6: 0.7 | T6: 75000 | U6: 1400 | V6: 790 | W6: 499 | X6: 0.8
A7: Grand Total | B7: 206601 | C7: 199310 | D7: 7291 | E7: 3611 | F7: 8422 | G7: 5058 | H7: 0.12666667 | I7: 0.39333333 | J7: 0.17333333 | K7: 0.30666667 | L7: 0.8 | M7: 0.76666667 | N7: 0.76666667 | O7: 0.73333333 | P7: 0.73333333 | Q7: 0.73333333 | R7: 0.7 | S7: 0.7 | T7: 225000 | U7: 4200 | V7: 2469 | W7: 1142 | X7: 0.8
A20: Row Labels | B20: Sum of Revenue | C20: Sum of Expenses | D20: Sum of Profit | E20: Sum of Sales Target | F20: Sum of Standart | G20: Sum of Premium | H20: Sum of Subscribers | I20: Sum of Subscribers Target | J20: Sum of Referral | K20: Sum of Social | L20: Sum of Organic | M20: Sum of Other
A21: JAN | B21: 59019 | C21: 67541 | D21: -8522 | E21: 75000 | F21: 538 | G21: 510 | H21: 1048 | I21: 1400 | J21: 0.15 | K21: 0.33 | L21: 0.16 | M21: 0.36
A22: FEB | B22: 81135 | C22: 62626 | D22: 18509 | E22: 75000 | F22: 797 | G22: 318 | H22: 1115 | I22: 1400 | J22: 0.22 | K22: 0.45 | L22: 0.22333333 | M22: 0.10666667
A23: MAR | B23: 84342 | C23: 68752 | D23: 15590 | E23: 75000 | F23: 565 | G23: 540 | H23: 1105 | I23: 1400 | J23: 0.17 | K23: 0.38 | L23: 0.18333333 | M23: 0.26666667
A24: APR | B24: 73245 | C24: 78653 | D24: -5408 | E24: 75000 | F24: 882 | G24: 325 | H24: 1207 | I24: 1400 | J24: 0.08 | K24: 0.41 | L24: 0.16333333 | M24: 0.34666667
A25: MAY | B25: 57139 | C25: 73540 | D25: -16401 | E25: 75000 | F25: 597 | G25: 611 | H25: 1208 | I25: 1400 | J25: 0.06 | K25: 0.23 | L25: 0.096666667 | M25: 0.61333333
A26: JUN | B26: 44835 | C26: 61426 | D26: -16591 | E26: 75000 | F26: 645 | G26: 616 | H26: 1261 | I26: 1400 | J26: 0.09 | K26: 0.23 | L26: 0.10666667 | M26: 0.57333333
A27: JUL | B27: 52221 | C27: 58031 | D27: -5810 | E27: 75000 | F27: 790 | G27: 499 | H27: 1289 | I27: 1400 | J27: 0.08 | K27: 0.32 | L27: 0.13333333 | M27: 0.46666667
A28: AUG | B28: 96718 | C28: 65713 | D28: 31005 | E28: 75000 | F28: 996 | G28: 431 | H28: 1427 | I28: 1400 | J28: 0.09 | K28: 0.24 | L28: 0.11 | M28: 0.56
A29: SEP | B29: 111028 | C29: 80943 | D29: 30085 | E29: 75000 | F29: 1183 | G29: 210 | H29: 1393 | I29: 1400 | J29: 0.19 | K29: 0.4 | L29: 0.19666667 | M29: 0.21333333
A30: OCT | B30: 105644 | C30: 89819 | D30: 15825 | E30: 75000 | F30: 876 | G30: 516 | H30: 1392 | I30: 1400 | J30: 0.16 | K30: 0.5 | L30: 0.22 | M30: 0.12
A31: NOV | B31: 77026 | C31: 85029 | D31: -8003 | E31: 75000 | F31: 1101 | G31: 406 | H31: 1507 | I31: 1400 | J31: 0.24 | K31: 0.33 | L31: 0.19 | M31: 0.24
A32: DEC | B32: 90717 | C32: 74016 | D32: 16701 | E32: 75000 | F32: 1269 | G32: 197 | H32: 1466 | I32: 1400 | J32: 0.06 | K32: 0.3 | L32: 0.12 | M32: 0.52
A33: Grand Total | B33: 933069 | C33: 866089 | D33: 66980 | E33: 900000 | F33: 10239 | G33: 5179 | H33: 15418 | I33: 16800 | J33: 1.59 | K33: 4.12 | L33: 1.9033333 | M33: 4.3866667
A35: Row Labels | B35: Sum of Subscribers
A36: 2027 | B36: 3611
A37: Grand Total | B37: 3611
A42: Row Labels | B42: Sum of Subscribers
A43: 2025 | B43: 3873
A44: 2026 | B44: 9235
A45: 2027 | B45: 15418
A46: 2028 | B46: 21089
A47: Grand Total | B47: 49615
A50: Row Labels
A51: Expenses
A52: Profit
A53: Revenue
A54: Grand Total
A57: Row Labels
A58: Standart
A59: Premium
A60: Grand Total
A62: Row Labels
A63: Social
A64: Grand Total

Sheet Data
A1: Year | B1: Month | C1: Revenue | D1: Expenses | E1: Sales Target | F1: Standart | G1: Premium | H1: Subscribers | I1: Subscribers Target | J1: Leads | K1: Deals | L1: Referral | M1: Social | N1: Organic | O1: Other | P1: N | Q1: NE | R1: E | S1: SE | T1: S | U1: SW | V1: W | W1: NW | X1: Coverage Target
A2: 2025 | B2: JAN | C2: 37835 | D2: 26660 | E2: 45000 | F2: 59 | G2: 41 | H2: 100 | I2: 300 | J2: 158 | K2: 138 | L2: 0.17 | M2: 0.48 | N2: 0.21666667 | O2: 0.13333333 | P2: 0.2 | Q2: 0.2 | R2: 0.2 | S2: 0.2 | T2: 0.2 | U2: 0.2 | V2: 0.2 | W2: 0.1 | X2: 0.5
A3: 2025 | B3: FEB | C3: 48805 | D3: 32060 | E3: 45000 | F3: 68 | G3: 67 | H3: 135 | I3: 300 | J3: 193 | K3: 193 | L3: 0.1 | M3: 0.31 | N3: 0.13666667 | O3: 0.45333333 | P3: 0.4 | Q3: 0.2 | R3: 0.2 | S3: 0.2 | T3: 0.2 | U3: 0.2 | V3: 0.2 | W3: 0.2 | X3: 0.5
A4: 2025 | B4: MAR | C4: 52169 | D4: 35760 | E4: 45000 | F4: 165 | G4: 42 | H4: 207 | I4: 300 | J4: 602 | K4: 335 | L4: 0.08 | M4: 0.37 | N4: 0.15 | O4: 0.4 | P4: 0.4 | Q4: 0.4 | R4: 0.2 | S4: 0.2 | T4: 0.2 | U4: 0.2 | V4: 0.2 | W4: 0.2 | X4: 0.5
A5: 2025 | B5: APR | C5: 47883 | D5: 36560 | E5: 45000 | F5: 151 | G5: 131 | H5: 282 | I5: 300 | J5: 569 | K5: 386 | L5: 0.24 | M5: 0.33 | N5: 0.19 | O5: 0.24 | P5: 0.4 | Q5: 0.4 | R5: 0.4 | S5: 0.2 | T5: 0.2 | U5: 0.2 | V5: 0.2 | W5: 0.2 | X5: 0.5
A6: 2025 | B6: MAY | C6: 39309 | D6: 34220 | E6: 45000 | F6: 117 | G6: 53 | H6: 170 | I6: 300 | J6: 336 | K6: 210 | L6: 0.08 | M6: 0.4 | N6: 0.16 | O6: 0.36 | P6: 0.4 | Q6: 0.4 | R6: 0.4 | S6: 0.4 | T6: 0.2 | U6: 0.2 | V6: 0.2 | W6: 0.2 | X6: 0.5
A7: 2025 | B7: JUN | C7: 31455 | D7: 29500 | E7: 45000 | F7: 230 | G7: 63 | H7: 293 | I7: 300 | J7: 471 | K7: 345 | L7: 0.14 | M7: 0.39 | N7: 0.17666667 | O7: 0.29333333 | P7: 0.4 | Q7: 0.4 | R7: 0.4 | S7: 0.4 | T7: 0.4 | U7: 0.2 | V7: 0.2 | W7: 0.2 | X7: 0.5
A8: 2025 | B8: JUL | C8: 31175 | D8: 23820 | E8: 45000 | F8: 270 | G8: 136 | H8: 406 | I8: 300 | J8: 840 | K8: 604 | L8: 0.19 | M8: 0.28 | N8: 0.15666667 | O8: 0.37333333 | P8: 0.4 | Q8: 0.4 | R8: 0.4 | S8: 0.4 | T8: 0.4 | U8: 0.4 | V8: 0.2 | W8: 0.2 | X8: 0.5
A9: 2025 | B9: AUG | C9: 43810 | D9: 19100 | E9: 45000 | F9: 318 | G9: 96 | H9: 414 | I9: 300 | J9: 1010 | K9: 554 | L9: 0.14 | M9: 0.39 | N9: 0.17666667 | O9: 0.29333333 | P9: 0.4 | Q9: 0.4 | R9: 0.4 | S9: 0.4 | T9: 0.4 | U9: 0.4 | V9: 0.4 | W9: 0.2 | X9: 0.5
A10: 2025 | B10: SEP | C10: 50097 | D10: 16760 | E10: 45000 | F10: 352 | G10: 53 | H10: 405 | I10: 300 | J10: 599 | K10: 542 | L10: 0.19 | M10: 0.24 | N10: 0.14333333 | O10: 0.42666667 | P10: 0.4 | Q10: 0.4 | R10: 0.4 | S10: 0.4 | T10: 0.4 | U10: 0.4 | V10: 0.4 | W10: 0.4 | X10: 0.5
A11: 2025 | B11: OCT | C11: 50762 | D11: 17560 | E11: 45000 | F11: 323 | G11: 163 | H11: 486 | I11: 300 | J11: 763 | K11: 568 | L11: 0.17 | M11: 0.22 | N11: 0.13 | O11: 0.48 | P11: 0.55 | Q11: 0.4 | R11: 0.4 | S11: 0.4 | T11: 0.4 | U11: 0.4 | V11: 0.4 | W11: 0.4 | X11: 0.5
A12: 2025 | B12: NOV | C12: 45773 | D12: 21260 | E12: 45000 | F12: 284 | G12: 165 | H12: 449 | I12: 300 | J12: 1279 | K12: 682 | L12: 0.17 | M12: 0.26 | N12: 0.14333333 | O12: 0.42666667 | P12: 0.55 | Q12: 0.55 | R12: 0.4 | S12: 0.4 | T12: 0.4 | U12: 0.4 | V12: 0.4 | W12: 0.4 | X12: 0.5
A13: 2025 | B13: DEC | C13: 46402 | D13: 26660 | E13: 45000 | F13: 235 | G13: 291 | H13: 526 | I13: 300 | J13: 878 | K13: 552 | L13: 0.21 | M13: 0.45 | N13: 0.22 | O13: 0.12 | P13: 0.55 | Q13: 0.55 | R13: 0.55 | S13: 0.4 | T13: 0.4 | U13: 0.4 | V13: 0.4 | W13: 0.4 | X13: 0.5
... A49: 2028 | B49: DEC | C49: 112126 | D49: 110400 | E49: 100000 | F49: 1798 | G49: 202 | H49: 2000 | I49: 1800 | J49: 3940 | K49: 2640 | L49: 0.12 | M49: 0.23 | N49: 0.11666667 | O49: 0.53333333 | P49: 1 | Q49: 1 | R49: 1 | S49: 1 | T49: 1 | U49: 1 | V49: 1 | W49: 1 | X49: 1

Sheet Resources
B3: E993EB
B4: 394CA9
B6: #5987F6
B7: #7A59CD
B9: #F0F8FD
B10: #A2D8F0
B12: #61A7F5
